LICENSE
pipechain/__init__.py
pipechain-0.1.1.dist-info/LICENSE
pipechain-0.1.1.dist-info/WHEEL
pipechain-0.1.1.dist-info/METADATA
pipechain-0.1.1.dist-info/RECORD
