Metadata-Version: 2.1
Name: pipechain
Version: 0.1.1
Summary: Functional pipelines in Python using method chaining
Home-page: https://github.com/multimeric/PipeChain
License: MIT
Author: Michael Milton
Author-email: michael.r.milton@gmail.com
Requires-Python: >=3.7,<3.11
Classifier: License :: OSI Approved :: MIT License
Classifier: Programming Language :: Python :: 3
Classifier: Programming Language :: Python :: 3.7
Classifier: Programming Language :: Python :: 3.8
Classifier: Programming Language :: Python :: 3.9
Project-URL: Repository, https://github.com/multimeric/PipeChain
